mdnet/__init__.py
mdnet/mdnet.py
mdnet/rss_generator.py
mdnet/setup.py
mdnet-0.1.9.dist-info/METADATA
mdnet-0.1.9.dist-info/WHEEL
mdnet-0.1.9.dist-info/entry_points.txt
mdnet-0.1.9.dist-info/top_level.txt
mdnet-0.1.9.dist-info/RECORD
