Metadata-Version: 2.1
Name: mdnet
Version: 0.1.9
Requires-Dist: markdown
Requires-Dist: jinja2
Requires-Dist: python-frontmatter
Requires-Dist: feedgen
Requires-Dist: pytz
